robotpy_build/__init__.py
robotpy_build/__main__.py
robotpy_build/download.py
robotpy_build/maven.py
robotpy_build/overrides.py
robotpy_build/pkgcfg.py
robotpy_build/pkgcfg_provider.py
robotpy_build/platforms.py
robotpy_build/relink_libs.py
robotpy_build/setup.py
robotpy_build/static_libs.py
robotpy_build/version.py
robotpy_build/wrapper.py
robotpy_build/autowrap/__init__.py
robotpy_build/autowrap/buffer.py
robotpy_build/autowrap/context.py
robotpy_build/autowrap/cxxparser.py
robotpy_build/autowrap/generator_data.py
robotpy_build/autowrap/mangle.py
robotpy_build/autowrap/render_cls_prologue.py
robotpy_build/autowrap/render_cls_rpy_include.py
robotpy_build/autowrap/render_pybind11.py
robotpy_build/autowrap/render_tmpl_inst.py
robotpy_build/autowrap/render_wrapped.py
robotpy_build/autowrap/writer.py
robotpy_build/command/__init__.py
robotpy_build/command/_built_env.py
robotpy_build/command/build_dl.py
robotpy_build/command/build_ext.py
robotpy_build/command/build_gen.py
robotpy_build/command/build_py.py
robotpy_build/command/build_pyi.py
robotpy_build/command/develop.py
robotpy_build/command/editable_wheel.py
robotpy_build/command/update_init.py
robotpy_build/command/util.py
robotpy_build/config/__init__.py
robotpy_build/config/autowrap_yml.py
robotpy_build/config/dev_yml.py
robotpy_build/config/pyproject_toml.py
robotpy_build/config/util.py
robotpy_build/include/gilsafe_object.h
robotpy_build/include/pybind11_typing.h
robotpy_build/include/robotpy_build.h
robotpy_build/pybind11/LICENSE
robotpy_build/pybind11/include/pybind11/attr.h
robotpy_build/pybind11/include/pybind11/buffer_info.h
robotpy_build/pybind11/include/pybind11/cast.h
robotpy_build/pybind11/include/pybind11/chrono.h
robotpy_build/pybind11/include/pybind11/common.h
robotpy_build/pybind11/include/pybind11/complex.h
robotpy_build/pybind11/include/pybind11/eigen.h
robotpy_build/pybind11/include/pybind11/embed.h
robotpy_build/pybind11/include/pybind11/eval.h
robotpy_build-2025.1.3.dist-info/METADATA
robotpy_build-2025.1.3.dist-info/WHEEL
robotpy_build-2025.1.3.dist-info/entry_points.txt
robotpy_build-2025.1.3.dist-info/licenses/LICENSE.txt
robotpy_build-2025.1.3.dist-info/licenses/robotpy_build/pybind11/LICENSE
robotpy_build-2025.1.3.dist-info/RECORD
