Metadata-Version: 2.4
Name: robotpy-build
Version: 2025.1.3
Summary: Build tool for RobotPy projects
Project-URL: Source code, https://github.com/robotpy/robotpy-build
Author-email: Dustin Spicuzza <robotpy@googlegroups.com>
License-Expression: BSD-3-Clause
License-File: LICENSE.txt
License-File: robotpy_build/pybind11/LICENSE
Classifier: Development Status :: 5 - Production/Stable
Classifier: Intended Audience :: Developers
Classifier: License :: OSI Approved :: BSD License
Classifier: Programming Language :: Python :: 3 :: Only
Classifier: Programming Language :: Python :: 3.8
Classifier: Programming Language :: Python :: 3.9
Classifier: Programming Language :: Python :: 3.10
Classifier: Programming Language :: Python :: 3.11
Classifier: Topic :: Software Development
Requires-Python: >=3.8
Requires-Dist: cxxheaderparser[pcpp]~=1.4.1
Requires-Dist: delocate; platform_system == 'Darwin'
Requires-Dist: distro; platform_system == 'Linux'
Requires-Dist: patch==1.*
Requires-Dist: pybind11-stubgen~=2.5.1
Requires-Dist: pydantic!=1.10.20,<2,>=1.7.0
Requires-Dist: pyyaml>=5.1
Requires-Dist: setuptools-scm<8,>=6.2
Requires-Dist: setuptools>=45
Requires-Dist: sphinxify>=0.7.3
Requires-Dist: tomli
Requires-Dist: tomli-w
Requires-Dist: toposort
Requires-Dist: typing-extensions
